xl2md/__init__.py
xl2md/__main__.py
xl2md/converter.py
xl2md-1.2.dist-info/licenses/LICENSE
xl2md-1.2.dist-info/METADATA
xl2md-1.2.dist-info/WHEEL
xl2md-1.2.dist-info/entry_points.txt
xl2md-1.2.dist-info/top_level.txt
xl2md-1.2.dist-info/RECORD
