Metadata-Version: 2.4
Name: xl2md
Version: 1.2
Summary: A fast and configurable CLI tool and library for converting Excel sheets into clean Markdown tables.
Author-email: "UST Global Inc." <nagurshareef.shaik@ust.com>
Maintainer-email: Nagur Shareef Shaik <nagurshareef.shaik@ust.com>
License: MIT License
Project-URL: Homepage, https://github.com/UST-Global-GenAI/xl2md
Project-URL: Documentation, https://github.com/UST-Global-GenAI/xl2md/blob/main/README.md
Project-URL: Bug Tracker, https://github.com/UST-Global-GenAI/xl2md/issues
Project-URL: Organization, https://www.ust.com/
Keywords: excel,markdown,converter,pandas,automation,cli,xlsx
Classifier: Development Status :: 4 - Beta
Classifier: Programming Language :: Python :: 3
Classifier: Programming Language :: Python :: 3.8
Classifier: Programming Language :: Python :: 3.9
Classifier: Programming Language :: Python :: 3.10
Classifier: Programming Language :: Python :: 3.11
Classifier: License :: OSI Approved :: MIT License
Classifier: Operating System :: OS Independent
Classifier: Intended Audience :: Developers
Classifier: Topic :: Office/Business
Classifier: Topic :: Text Processing :: Markup
Classifier: Topic :: Utilities
Requires-Python: >=3.8
License-File: LICENSE
Requires-Dist: pandas
Requires-Dist: openpyxl
Dynamic: license-file
